{
    "num": 4,
    "date": "2020-12-06 18:20:01",
    "media_id": "2458355226338827977",
    "shortcode": "CId1Q2tpp7J",
    "display_url": "https://scontent-lhr8-2.cdninstagram.com/v/t51.29350-15/128644094_400604354706954_5416672477125694995_n.jpg?stp=dst-jpg_e35_tt6&efg=eyJ2ZW5jb2RlX3RhZyI6IkNBUk9VU0VMX0lURU0uaW1hZ2VfdXJsZ2VuLjEwNzh4MTM1MC5zZHIuZjI5MzUwLmRlZmF1bHRfaW1hZ2UuYzIifQ&_nc_ht=scontent-lhr8-2.cdninstagram.com&_nc_cat=106&_nc_oc=Q6cZ2QHs_Tl38CK-j2AdqpjY_hED4gSEF780gGbldTHjJ6cwyajHacGxEeInxvDowelCVyeuQaJ_jmz4qAsv39eThHrQ&_nc_ohc=B9x8sTI1T0oQ7kNvwGwpmns&_nc_gid=QRyUJ-SPvqjuMIx2v6eYTQ&edm=ACOOH6wBAAAA&ccb=7-5&ig_cache_key=MjQ1ODM1NTIyNjMzODgyNzk3Nw%3D%3D.3-ccb7-5&oh=00_AfiP3vo3eKz7ZOt4FweHkwv6Vd3S4RA1YDfVtTdCLDaX1A&oe=690F1559&_nc_sid=aa4e97",
    "video_url": null,
    "width": 1078,
    "height": 1350,
    "tagged_users": [],
    "post_id": "2458355230373670701",
    "post_shortcode": "CId1Q6eJW8t",
    "likes": 8134,
    "liked": false,
    "pinned": [],
    "description": "4 iconic places of Paris under the snow ❤ Which picture do you prefer :\n1. Champs de Mars / Eiffel Tower\n2. Alexander lll Bridge\n3. Place des Vosges\n4. Sacré Cœur/ Montmartre😀\n.\nGreat pictures by @herve_in_paris ⭐⭐⭐\n.\nFounders: @jerry_and_lucy 👋 DM for promotions / collaborations or send an email at unlimitedvisibility@gmail.com 👍\n.\nFollow @parisluxurylifestyle\nFor more great content about Paris ❤\n.\nShare your best pictures of #paris with #parisluxurylifestyle ❤ #topparisphoto #unlimitedparis #parisluxurylife #luxuryparis #parisluxury #parisfrance #igersparis #parisjetaime #luxuryplace #luxuryparis #parisluxury #parisluxe #architectureparis #parismonamour #luxuryhotels #luxurytravel #thisisparis #parisarchitecture #parissecret #parisianstyle #eiffeltower #toureiffel #eiffeltowerparis #eiffeltower🗼 #toureiffel🗼",
    "tags": [
        "#architectureparis",
        "#eiffeltower",
        "#eiffeltowerparis",
        "#igersparis",
        "#luxuryhotels",
        "#luxuryparis",
        "#luxuryplace",
        "#luxurytravel",
        "#paris",
        "#parisarchitecture",
        "#parisfrance",
        "#parisianstyle",
        "#parisjetaime",
        "#parisluxe",
        "#parisluxury",
        "#parisluxurylife",
        "#parisluxurylifestyle",
        "#parismonamour",
        "#parissecret",
        "#thisisparis",
        "#topparisphoto",
        "#toureiffel",
        "#unlimitedparis"
    ],
    "location_id": "6889842",
    "location_slug": "paris",
    "location_url": "https://www.instagram.com/explore/locations/6889842/paris/",
    "sidecar_media_id": "2458355230373670701",
    "sidecar_shortcode": "CId1Q6eJW8t",
    "owner_id": "2701803548",
    "username": "parisluxurylifestyle",
    "fullname": "Paris Luxury Lifestyle",
    "post_date": "2020-12-06 18:20:02",
    "type": "post",
    "post_url": "https://www.instagram.com/p/CId1Q6eJW8t/",
    "count": 4,
    "category": "instagram",
    "subcategory": "saved",
    "filename": "128644094_400604354706954_5416672477125694995_n",
    "extension": "jpg"
}
