{
    "num": 3,
    "date": "2023-09-24 05:04:20",
    "media_id": "3198675511463742350",
    "shortcode": "Cxj-m4siYuO",
    "display_url": "https://scontent-lhr8-1.cdninstagram.com/v/t39.30808-6/484984355_675419955022447_4096432176144507629_n.jpg?stp=dst-jpg_e35_tt6&_nc_cat=111&ig_cache_key=MzE5ODY3NTUxMTQ2Mzc0MjM1MA%3D%3D.3-ccb1-7&ccb=1-7&_nc_sid=58cdad&efg=eyJ2ZW5jb2RlX3RhZyI6InhwaWRzLjEwODB4MTMwMS5zZHIuQzMifQ%3D%3D&_nc_ohc=1caK5vR0Wx8Q7kNvwH-Nndq&_nc_oc=AdlwX7hdQTmo52uxWdrsmQXr64uAIpdFc5qwjc63eOnYIoO2JyJpRsgd9qktLTJUFfqkftH5YsH1ZF-2F22F1U-p&_nc_ad=z-m&_nc_cid=0&_nc_zt=23&_nc_ht=scontent-lhr8-1.cdninstagram.com&_nc_gid=T5NcD65ujB3jfJhSgH1cUg&oh=00_Afh98cTizf5YkSmaxsQxGqNWpNk10VxZrlwEfQfFPEKqcw&oe=690F1AE8",
    "video_url": null,
    "width": 1080,
    "height": 1301,
    "tagged_users": [],
    "post_id": "3198675549782989080",
    "post_shortcode": "Cxj-ncYitkY",
    "likes": 9978,
    "liked": false,
    "pinned": [],
    "description": "Which image is your favourite ??\nQuale immagine è la tua preferita ??\nScegli il tuo scatto preferito tagga un amico e condividi sul tuo story...!!\n1- Val di Funes @timphilippus\n2- Canale di Tenno @artur.alla\n3- Lago di Dobbiaco @font93\n4- Rifugio Lago Nambino @arturlandscapes\n5- Lago di Carezza @blackmountain__\n6- Le Odle @trekwithartur\n7- Tre Cime di Lavaredo @marioshsmith @maufderlauer\n8- Val di Fumo @artur.alla\n9- Lago di Antermoia @simone.zafrani\n10- Lago di Resia @teo_barla_",
    "location_id": "263713776",
    "location_slug": "trentino-alto-adige/südtirol",
    "location_url": "https://www.instagram.com/explore/locations/263713776/trentino-alto-adige/südtirol/",
    "sidecar_media_id": "3198675549782989080",
    "sidecar_shortcode": "Cxj-ncYitkY",
    "owner_id": "47240648426",
    "username": "arturtrekkingdolomiti",
    "fullname": "Artur | Trekking Vanlife Dolomiti",
    "post_date": "2023-09-24 05:04:21",
    "type": "post",
    "post_url": "https://www.instagram.com/p/Cxj-ncYitkY/",
    "count": 10,
    "category": "instagram",
    "subcategory": "saved",
    "filename": "484984355_675419955022447_4096432176144507629_n",
    "extension": "jpg"
}
