[
    {
        "text": "\ud83d\udccd : Florence, Italy ",
        "start": 0,
        "end": 20,
        "groupdict": {
            "icon": "\ud83d\udccd",
            "location": " : Florence, Italy "
        },
        "method": "rule",
        "rule": "icon"
    },
    {
        "text": "\ud83c\uddee\ud83c\uddf9",
        "start": 20,
        "end": 22,
        "groupdict": {
            "flag": "\ud83c\uddee\ud83c\uddf9",
            "location": "Italy"
        },
        "method": "rule",
        "rule": "country",
        "attr": "flag"
    },
    {
        "text": "Italy",
        "start": 14,
        "end": 19,
        "groupdict": {
            "name": "Italy",
            "location": "Italy"
        },
        "method": "rule",
        "rule": "country",
        "attr": "text"
    }
]