{
    "num": 10,
    "date": "2023-07-02 14:25:16",
    "media_id": "3138076705340370335",
    "shortcode": "CuMsCMjva2f",
    "display_url": "https://scontent-lhr6-1.cdninstagram.com/v/t51.29350-15/357196692_937358300855018_5852197124936734259_n.jpg?stp=dst-jpg_e35_tt6&efg=eyJ2ZW5jb2RlX3RhZyI6IkNBUk9VU0VMX0lURU0uaW1hZ2VfdXJsZ2VuLjE0NDB4MTc0MS5zZHIuZjI5MzUwLmRlZmF1bHRfaW1hZ2UuYzIifQ&_nc_ht=scontent-lhr6-1.cdninstagram.com&_nc_cat=102&_nc_oc=Q6cZ2QEPVNb9On51OYillnf-p7rQyZksbUK3vEqZtABZP2SrXefZTpo1VfViAnwjZKfoXKAYkKdnX_rE-mwWjhqrPJq1&_nc_ohc=gN3P_jqNrmUQ7kNvwHXThhX&_nc_gid=AYOiBPeN0QoyRui0w5Iucg&edm=ACOOH6wBAAAA&ccb=7-5&ig_cache_key=MzEzODA3NjcwNTM0MDM3MDMzNQ%3D%3D.3-ccb7-5&oh=00_Afh6k2cw6pdqoHyACdAxhdIBS_UaiDQD5aTp9p50-_eKtw&oe=690F3615&_nc_sid=aa4e97",
    "video_url": null,
    "width": 1440,
    "height": 1741,
    "tagged_users": [],
    "post_id": "3138076710910374047",
    "post_shortcode": "CuMsCRvvTCf",
    "likes": 3,
    "liked": false,
    "pinned": [],
    "description": "All you can hear is the sounds of water and breeze.\n.\n#hellofrom Kyoto\n.\n\n#zen\n#hypebeast\n#citykillerz\n#streetgrammer\n#urbanromantix\n#citygrammers \n#team_jp_ \n#japantrip\n#streets_vision\n#visitjapanjp\n#moodygrams \n#sonyalpha\n#bealpha\n#japan_daytime_view \n#stayandwander\n#tokyocameraclub\n#art_of_japan_\n#streetclassics \n#japan_city_blues\n#voyaged\n#beautifuldestinations\n#travellingthroughtheworld\n#yourshotphotographer\n#earthpix\n#roamtheplanet\n#discoverearth\n#kyoto",
    "tags": [
        "#art_of_japan_",
        "#bealpha",
        "#beautifuldestinations",
        "#citygrammers",
        "#citykillerz",
        "#discoverearth",
        "#earthpix",
        "#hellofrom",
        "#hypebeast",
        "#japan_city_blues",
        "#japan_daytime_view",
        "#japantrip",
        "#kyoto",
        "#moodygrams",
        "#roamtheplanet",
        "#sonyalpha",
        "#stayandwander",
        "#streetclassics",
        "#streetgrammer",
        "#streets_vision",
        "#team_jp_",
        "#tokyocameraclub",
        "#travellingthroughtheworld",
        "#urbanromantix",
        "#visitjapanjp",
        "#voyaged",
        "#yourshotphotographer",
        "#zen"
    ],
    "location_id": "2149871441941704",
    "location_slug": "kifune-jinja-shrine",
    "location_url": "https://www.instagram.com/explore/locations/2149871441941704/kifune-jinja-shrine/",
    "sidecar_media_id": "3138076710910374047",
    "sidecar_shortcode": "CuMsCRvvTCf",
    "owner_id": "6293727021",
    "username": "tokyo.ig",
    "fullname": "TOKYO.IG",
    "post_date": "2023-07-02 14:25:16",
    "type": "post",
    "post_url": "https://www.instagram.com/p/CuMsCRvvTCf/",
    "count": 10,
    "category": "instagram",
    "subcategory": "saved",
    "filename": "357196692_937358300855018_5852197124936734259_n",
    "extension": "jpg"
}
