{
    "num": 7,
    "date": "2021-12-30 07:42:28",
    "media_id": "2739972093166813510",
    "shortcode": "CYGVhoLsQFG",
    "display_url": "https://scontent-lhr8-2.cdninstagram.com/v/t51.29350-15/270271993_3038361693080691_4559321344585612601_n.jpg?stp=dst-jpg_e35_tt6&efg=eyJ2ZW5jb2RlX3RhZyI6IkNBUk9VU0VMX0lURU0uaW1hZ2VfdXJsZ2VuLjE0NDB4MTgwMC5zZHIuZjI5MzUwLmRlZmF1bHRfaW1hZ2UuYzIifQ&_nc_ht=scontent-lhr8-2.cdninstagram.com&_nc_cat=103&_nc_oc=Q6cZ2QHuJSm_eWw0_81BgN3M2b8nHDIy6mBy_wvFbflKbtMwQudqGNOl7EsbHIpM0IjL2jIR47IQbI-2p4v1aLJdVQCD&_nc_ohc=wmEpYuod4-UQ7kNvwErd-fu&_nc_gid=bq2ttnHOtPoPKZc2E4TF7g&edm=ACOOH6wBAAAA&ccb=7-5&ig_cache_key=MjczOTk3MjA5MzE2NjgxMzUxMA%3D%3D.3-ccb7-5&oh=00_Afj8Qlq4LUJp_fAe1OPsnT1acxiVX11MM0e4Z3gLPPNTKg&oe=690F38FD&_nc_sid=aa4e97",
    "video_url": null,
    "width": 1440,
    "height": 1800,
    "tagged_users": [],
    "post_id": "2739972097554141761",
    "post_shortcode": "CYGVhsRMlJB",
    "likes": 6976,
    "liked": false,
    "pinned": [],
    "description": "📸 #españa #granada 🇪🇸 \n\n@shootwithjuan \n\nT A G  #ig_spain_ #spain #ig_spain #mediterranean #mediterraneo \nA D M I N  Spain igworldclub Team\n\nG R U P O  @igworldclub\nM I E M B R O S  @igworldclub_officialaccount\nC O N T A C T O  igworldclub@gmail.com\n\n#spainvacation #tour_espana #spain_in_bl #ok_spain #be_one_spain #estaes_espania #world_spain #fever_spain #visitspain #total_europe #lifeofspain #turismospain #igersspain #monumentalspain #monumentaleurope #spain_greatshots  #spainwonderful #🇪🇸.",
    "tags": [
        "#be_one_spain",
        "#españa",
        "#estaes_espania",
        "#fever_spain",
        "#granada",
        "#ig_spain",
        "#ig_spain_",
        "#igersspain",
        "#lifeofspain",
        "#mediterranean",
        "#mediterraneo",
        "#monumentaleurope",
        "#monumentalspain",
        "#ok_spain",
        "#spain",
        "#spain_greatshots",
        "#spain_in_bl",
        "#spainvacation",
        "#spainwonderful",
        "#total_europe",
        "#tour_espana",
        "#turismospain",
        "#visitspain",
        "#world_spain"
    ],
    "location_id": "215187911",
    "location_slug": "granada",
    "location_url": "https://www.instagram.com/explore/locations/215187911/granada/",
    "sidecar_media_id": "2739972097554141761",
    "sidecar_shortcode": "CYGVhsRMlJB",
    "owner_id": "1152679816",
    "username": "ig_spain_",
    "fullname": "SPAIN 🇪🇸",
    "post_date": "2021-12-30 07:42:28",
    "type": "post",
    "post_url": "https://www.instagram.com/p/CYGVhsRMlJB/",
    "count": 10,
    "category": "instagram",
    "subcategory": "saved",
    "filename": "270271993_3038361693080691_4559321344585612601_n",
    "extension": "jpg"
}
