{
    "node": {
        "id": "2638172242989759545",
        "__typename": "GraphImage",
        "edge_media_to_caption": {
            "edges": [
                {
                    "node": {
                        "text": "\ud83d\udccdTransylvania, Romania \nWhere is your favourite place to visit?\ud83c\uddf7\ud83c\uddf4\u2665\ufe0f\nTag all your travel besties\u2757\ufe0f\n\nFollow \u2014> @escapetoeurope \nFollow \u2014> @escapetoeurope\n\n\ud83e\udde0It\u2019s home to the world\u2019s heaviest building. Bucharest\u2019s vast Palace of the Parliament, begun during the final years of Nicolae Ceau\u0219escu\u2019s rule and not finished until 1997 (seven years after his death), is 240 metres long, 270 metres wide, 86 metres high (12 storeys), and cost a staggering \u20ac3 billion (\u00a32.5bn) to build\u2757\ufe0f\n\nCredit to @bokehm0n and @map_of_europe \n\n#escapetoeurope #europe #travel #travels #travelblogger #earth #placestovisit #dreamdestinations #discovertheglobe #travelaway #travelenthusiast #travelforlife #traveldestinations #travelblog #travelblogger #travellingthroughtheworld #beautifuldestinations #traveloften #picoftheday #travelineurope #travelaway #topdestinations #travelstagram #travelphotography #instaeurope #rom\u00e2nia #romania #romaniatravel #transylvania #romania\ud83c\uddf9\ud83c\udde9"
                    }
                }
            ]
        },
        "shortcode": "CScq61nszw5",
        "edge_media_to_comment": {
            "count": 45
        },
        "comments_disabled": false,
        "taken_at_timestamp": 1628714660,
        "dimensions": {
            "height": 1341,
            "width": 1080
        },
        "display_url": "https://scontent-lhr8-2.cdninstagram.com/v/t51.2885-15/236233003_1641751322688529_1324896362159501890_n.jpg?stp=dst-jpg_e35_p1080x1080&_nc_ht=scontent-lhr8-2.cdninstagram.com&_nc_cat=101&_nc_ohc=PjO9vHvZpc0AX_otG7V&edm=APaBKmcBAAAA&ccb=7-5&oh=00_AfBDIYzM9MPoxXBcXs7gatDFR2pS2qn-cIOYDr-fMm5NXg&oe=654BA1BE&_nc_sid=ef314d",
        "edge_liked_by": {
            "count": 2358
        },
        "edge_media_preview_like": {
            "count": 2358
        },
        "owner": {
            "id": "45015397260"
        },
        "thumbnail_src": "https://scontent-lhr8-2.cdninstagram.com/v/t51.2885-15/236233003_1641751322688529_1324896362159501890_n.jpg?stp=c0.174.1440.1440a_dst-jpg_e35_s640x640_sh0.08&_nc_ht=scontent-lhr8-2.cdninstagram.com&_nc_cat=101&_nc_ohc=PjO9vHvZpc0AX_otG7V&edm=APaBKmcBAAAA&ccb=7-5&oh=00_AfCs4Od4R8RXURnuLtSrTlBSFzKl75-XUWAud5XK5hoKpQ&oe=654BA1BE&_nc_sid=ef314d",
        "is_video": false
    },
    "instaloader": {
        "version": "4.10.1",
        "node_type": "Post"
    }
}