{
    "node": {
        "id": "2919234420366698752",
        "__typename": "GraphSidecar",
        "edge_media_to_caption": {
            "edges": [
                {
                    "node": {
                        "text": "From 1 to 10 which Vaporia photo is your favorite?\ud83c\uddec\ud83c\uddf7\ud83d\udc99\ud83e\uddff\ud83d\udca6 Happy weekend dear friends! \ud83c\udfb6\ud83c\udf89\ud83d\udc9d\ud83c\udf3c\ud83d\udc9a\ud83c\udfb5\u2764\ufe0f\n\n.\n.\n\ud83c\uddec\ud83c\uddf7\n.\n#beautifuldestinations #wonderful_places\n#bestplacestogo #travellingthroughtheworld\n#hello_worldpics #divine_worldplaces\n\u00a0#europestyle_  #travel_drops\n #discover_europe_ \n#perfect_greece  #wu_greece\n#greece_moments\u2028\u00a0#kings_greece \u2028#the_daily_traveller\u2028#exquisite_greece \u2028#loves_greece_ \u2028#expression_greece #athensvoice\n#tv_greece\n#topgreecephoto #thegreeceguide\u2028#heavenly_shotz  #hermoupolis \n#syrosisland #syros\n#syros_greece\n#vaporia  #ermoupolis #anosyros \n.\n.\n\ud83d\udccdSyros island, Cyclades, Greece."
                    }
                }
            ]
        },
        "shortcode": "CiDND0SDOkA",
        "edge_media_to_comment": {
            "count": 145
        },
        "comments_disabled": false,
        "taken_at_timestamp": 1662219883,
        "dimensions": {
            "height": 1349,
            "width": 1080
        },
        "display_url": "https://scontent-lhr6-1.cdninstagram.com/v/t51.2885-15/302565703_594112325596138_7800195910324935464_n.jpg?stp=dst-jpg_e35_p1080x1080&_nc_ht=scontent-lhr6-1.cdninstagram.com&_nc_cat=110&_nc_ohc=jQ5ar366mD0AX8la2co&edm=APaBKmcBAAAA&ccb=7-5&oh=00_AfB6QflRjhWk5-Dyum5toORNn7HmbfZPHzbYHhUML5uQ-g&oe=654C721D&_nc_sid=ef314d",
        "edge_liked_by": {
            "count": 11356
        },
        "edge_media_preview_like": {
            "count": 11356
        },
        "owner": {
            "id": "467697086"
        },
        "thumbnail_src": "https://scontent-lhr6-1.cdninstagram.com/v/t51.2885-15/302565703_594112325596138_7800195910324935464_n.jpg?stp=c0.179.1440.1440a_dst-jpg_e35_s640x640_sh0.08&_nc_ht=scontent-lhr6-1.cdninstagram.com&_nc_cat=110&_nc_ohc=jQ5ar366mD0AX8la2co&edm=APaBKmcBAAAA&ccb=7-5&oh=00_AfAHmpiLFVl7VMkE3Kvy5_hMrrUHb9Wh1d2kE8hHwJUWTw&oe=654C721D&_nc_sid=ef314d",
        "is_video": false
    },
    "instaloader": {
        "version": "4.10.1",
        "node_type": "Post"
    }
}