{
    "node": {
        "id": "3079558293381940360",
        "__typename": "GraphSidecar",
        "edge_media_to_caption": {
            "edges": [
                {
                    "node": {
                        "text": "Select by @mattberthou\n\ud83d\udcf8 : @yuri_vantowski \n\nSite : \ud83c\udff4\udb40\udc67\udb40\udc62\udb40\udc73\udb40\udc63\udb40\udc74\udb40\udc7f isle of skye"
                    }
                }
            ]
        },
        "shortcode": "Cq8yfOeI4SI",
        "edge_media_to_comment": {
            "count": 85
        },
        "comments_disabled": false,
        "taken_at_timestamp": 1681331978,
        "dimensions": {
            "height": 1350,
            "width": 1080
        },
        "display_url": "https://scontent-lhr6-1.cdninstagram.com/v/t51.2885-15/340646697_191370800352022_8522927849018251106_n.webp?stp=dst-jpg_e35_p1080x1080&_nc_ht=scontent-lhr6-1.cdninstagram.com&_nc_cat=110&_nc_ohc=A9chWdd-LyMAX9wIuUC&edm=APaBKmcBAAAA&ccb=7-5&oh=00_AfDWzN0KFbyXKiJOvNEEsCOlADnbRPq2ONr8qZ9Y1ruMDA&oe=654BBA24&_nc_sid=ef314d",
        "edge_liked_by": {
            "count": 11828
        },
        "edge_media_preview_like": {
            "count": 11828
        },
        "owner": {
            "id": "6890541826"
        },
        "thumbnail_src": "https://scontent-lhr6-1.cdninstagram.com/v/t51.2885-15/340646697_191370800352022_8522927849018251106_n.webp?stp=c0.180.1440.1440a_dst-jpg_e35_s640x640_sh0.08&_nc_ht=scontent-lhr6-1.cdninstagram.com&_nc_cat=110&_nc_ohc=A9chWdd-LyMAX9wIuUC&edm=APaBKmcBAAAA&ccb=7-5&oh=00_AfCBlCmYaJR5B8fUBVIO3i_WVjWtbYnK7vqnjS7a_hwdpg&oe=654BBA24&_nc_sid=ef314d",
        "is_video": false
    },
    "instaloader": {
        "version": "4.10.1",
        "node_type": "Post"
    }
}