{
    "node": {
        "id": "2845677362398542305",
        "__typename": "GraphSidecar",
        "edge_media_to_caption": {
            "edges": [
                {
                    "node": {
                        "text": "This views can't get better\ud83d\ude0d. Have you been to \ud83d\udccdValley of Fire State Park, Nevada?\n.\n\ud83c\uddfa\ud83c\uddf2Follow \ud83d\udc49@explore.the.usa \ud83d\udc48 For More Amazing Travelling Destinations.\n.\n\ud83d\udcf8@christopherballadarez @v_outdoors\ud83d\udcaf\n.\n.\n.\n.\n.\n.\n.\n.\n#archesnps #archesnationalpark\n#valleyoffirestatepark #travelnevada\n#valleyoffire  #nevadacityca  #utahroadtrip  #californiastateparks #nationalparkusa  #coastalhighway #californiaexplored #californiahiking #utahisbeautiful #roadtripusa  #nevadaroadtrip  #nevadastateparks  #yosemitenps #yosemitevillage  #roadtrip2020 #travelideas #yosemitelive #travelphotography #usatravel #usatour  #national_park_photography #nationalparkgeek #roadtripphotography #roadtripcalifornia #roadtripamerica"
                    }
                }
            ]
        },
        "shortcode": "Cd94HvrIrnh",
        "edge_media_to_comment": {
            "count": 99
        },
        "comments_disabled": false,
        "taken_at_timestamp": 1653451198,
        "dimensions": {
            "height": 1341,
            "width": 1080
        },
        "display_url": "https://scontent-lhr6-1.cdninstagram.com/v/t51.2885-15/283401020_3108890696075246_8237239210497364626_n.webp?stp=dst-jpg_e35&_nc_ht=scontent-lhr6-1.cdninstagram.com&_nc_cat=102&_nc_ohc=_4aj6nmYh5kAX8dcats&edm=APaBKmcBAAAA&ccb=7-5&oh=00_AfDRqDe2YuRNRXHXCHKfWKWQMIb2fptAa-9rFkCPX0_MGw&oe=654D6A09&_nc_sid=ef314d",
        "edge_liked_by": {
            "count": 19084
        },
        "edge_media_preview_like": {
            "count": 19084
        },
        "owner": {
            "id": "45197864514"
        },
        "thumbnail_src": "https://scontent-lhr6-1.cdninstagram.com/v/t51.2885-15/283401020_3108890696075246_8237239210497364626_n.webp?stp=c0.130.1079.1079a_dst-jpg_e35_s640x640_sh0.08&_nc_ht=scontent-lhr6-1.cdninstagram.com&_nc_cat=102&_nc_ohc=_4aj6nmYh5kAX8dcats&edm=APaBKmcBAAAA&ccb=7-5&oh=00_AfAWEj57QoYOYNL9b7YZHEeT4Sz9VRBO7FvTEMGKz9_FOA&oe=654D6A09&_nc_sid=ef314d",
        "is_video": false
    },
    "instaloader": {
        "version": "4.10.1",
        "node_type": "Post"
    }
}